<?xml version="1.0" encoding="UTF-8"?>
<sv:node xmlns:sv="http://www.jcp.org/jcr/sv/1.0" xmlns:xsi="http://www.w3.org/2001/XMLSchema-instance" sv:name="empleado_cione_fp_envios">
  <sv:property sv:name="jcr:primaryType" sv:type="Name">
    <sv:value>mgnl:role</sv:value>
  </sv:property>
  <sv:property sv:name="jcr:uuid" sv:type="String">
    <sv:value>4dbbefb5-23ae-4ed7-af04-68a6eed0562f</sv:value>
  </sv:property>
  <sv:property sv:name="mgnl:created" sv:type="Date">
    <sv:value>2021-02-09T09:32:58.187+01:00</sv:value>
  </sv:property>
  <sv:property sv:name="mgnl:createdBy" sv:type="String">
    <sv:value>superuser</sv:value>
  </sv:property>
  <sv:property sv:name="mgnl:lastModified" sv:type="Date">
    <sv:value>2021-02-09T09:32:58.571+01:00</sv:value>
  </sv:property>
  <sv:property sv:name="mgnl:lastModifiedBy" sv:type="String">
    <sv:value>superuser</sv:value>
  </sv:property>
  <sv:node sv:name="acl_userroles">
    <sv:property sv:name="jcr:primaryType" sv:type="Name">
      <sv:value>mgnl:contentNode</sv:value>
    </sv:property>
    <sv:property sv:name="jcr:uuid" sv:type="String">
      <sv:value>76fec737-f9ae-4a6d-9900-a17fef552d00</sv:value>
    </sv:property>
    <sv:property sv:name="mgnl:created" sv:type="Date">
      <sv:value>2021-02-09T09:32:58.188+01:00</sv:value>
    </sv:property>
    <sv:property sv:name="mgnl:createdBy" sv:type="String">
      <sv:value>superuser</sv:value>
    </sv:property>
    <sv:property sv:name="mgnl:lastModified" sv:type="Date">
      <sv:value>2021-02-09T09:32:58.188+01:00</sv:value>
    </sv:property>
    <sv:property sv:name="mgnl:lastModifiedBy" sv:type="String">
      <sv:value>superuser</sv:value>
    </sv:property>
    <sv:node sv:name="0">
      <sv:property sv:name="jcr:primaryType" sv:type="Name">
        <sv:value>mgnl:contentNode</sv:value>
      </sv:property>
      <sv:property sv:name="jcr:uuid" sv:type="String">
        <sv:value>9d652210-b9a5-4add-9e78-998f13a5c0e5</sv:value>
      </sv:property>
      <sv:property sv:name="mgnl:created" sv:type="Date">
        <sv:value>2021-02-09T09:32:58.189+01:00</sv:value>
      </sv:property>
      <sv:property sv:name="mgnl:createdBy" sv:type="String">
        <sv:value>superuser</sv:value>
      </sv:property>
      <sv:property sv:name="mgnl:lastModified" sv:type="Date">
        <sv:value>2021-02-09T09:32:58.189+01:00</sv:value>
      </sv:property>
      <sv:property sv:name="mgnl:lastModifiedBy" sv:type="String">
        <sv:value>superuser</sv:value>
      </sv:property>
      <sv:property sv:name="path" sv:type="String">
        <sv:value>/cione/empleado_cione_fp_envios</sv:value>
      </sv:property>
      <sv:property sv:name="permissions" sv:type="Long">
        <sv:value>8</sv:value>
      </sv:property>
    </sv:node>
  </sv:node>
  <sv:node sv:name="acl_website">
    <sv:property sv:name="jcr:primaryType" sv:type="Name">
      <sv:value>mgnl:contentNode</sv:value>
    </sv:property>
    <sv:property sv:name="jcr:uuid" sv:type="String">
      <sv:value>aace17da-4005-48d6-a21c-ec8aad1a1c95</sv:value>
    </sv:property>
    <sv:property sv:name="mgnl:created" sv:type="Date">
      <sv:value>2021-02-09T09:32:58.250+01:00</sv:value>
    </sv:property>
    <sv:property sv:name="mgnl:createdBy" sv:type="String">
      <sv:value>superuser</sv:value>
    </sv:property>
    <sv:property sv:name="mgnl:lastModified" sv:type="Date">
      <sv:value>2021-02-09T09:32:58.250+01:00</sv:value>
    </sv:property>
    <sv:property sv:name="mgnl:lastModifiedBy" sv:type="String">
      <sv:value>superuser</sv:value>
    </sv:property>
    <sv:node sv:name="0">
      <sv:property sv:name="jcr:primaryType" sv:type="Name">
        <sv:value>mgnl:contentNode</sv:value>
      </sv:property>
      <sv:property sv:name="jcr:uuid" sv:type="String">
        <sv:value>691ad128-d476-4ef5-bdb7-5f13deb947f6</sv:value>
      </sv:property>
      <sv:property sv:name="mgnl:created" sv:type="Date">
        <sv:value>2021-02-09T09:32:58.250+01:00</sv:value>
      </sv:property>
      <sv:property sv:name="mgnl:createdBy" sv:type="String">
        <sv:value>superuser</sv:value>
      </sv:property>
      <sv:property sv:name="mgnl:lastModified" sv:type="Date">
        <sv:value>2021-02-09T09:32:58.250+01:00</sv:value>
      </sv:property>
      <sv:property sv:name="mgnl:lastModifiedBy" sv:type="String">
        <sv:value>superuser</sv:value>
      </sv:property>
      <sv:property sv:name="path" sv:type="String">
        <sv:value>/cione/private/pedidos-facturacion/pedidos/consulta-envios</sv:value>
      </sv:property>
      <sv:property sv:name="permissions" sv:type="Long">
        <sv:value>0</sv:value>
      </sv:property>
    </sv:node>
    <sv:node sv:name="00">
      <sv:property sv:name="jcr:primaryType" sv:type="Name">
        <sv:value>mgnl:contentNode</sv:value>
      </sv:property>
      <sv:property sv:name="jcr:uuid" sv:type="String">
        <sv:value>bcb8d3cd-6214-44fd-85da-ab13d99d2036</sv:value>
      </sv:property>
      <sv:property sv:name="mgnl:created" sv:type="Date">
        <sv:value>2021-02-09T09:32:58.250+01:00</sv:value>
      </sv:property>
      <sv:property sv:name="mgnl:createdBy" sv:type="String">
        <sv:value>superuser</sv:value>
      </sv:property>
      <sv:property sv:name="mgnl:lastModified" sv:type="Date">
        <sv:value>2021-02-09T09:32:58.250+01:00</sv:value>
      </sv:property>
      <sv:property sv:name="mgnl:lastModifiedBy" sv:type="String">
        <sv:value>superuser</sv:value>
      </sv:property>
      <sv:property sv:name="path" sv:type="String">
        <sv:value>/cione/private/pedidos-facturacion/pedidos/consulta-envios/*</sv:value>
      </sv:property>
      <sv:property sv:name="permissions" sv:type="Long">
        <sv:value>0</sv:value>
      </sv:property>
    </sv:node>
  </sv:node>
</sv:node>
